coined_party/__init__.py
coined_party/__main__.py
coined_party/coined_party.py
coined_party-0.0.0a10.dist-info/licenses/LICENSE
coined_party-0.0.0a10.dist-info/METADATA
coined_party-0.0.0a10.dist-info/WHEEL
coined_party-0.0.0a10.dist-info/top_level.txt
coined_party-0.0.0a10.dist-info/RECORD
