Metadata-Version: 2.4
Name: coined_party
Version: 0.0.0a10
Summary: A text based party game that will soon destroy nintendo party games (cuz there's no way I even come close to BOTW).
Author-email: Yoosif Alquwatly <yalquwatly@gmail.com>
License: Copyright (c) 2025 Yoosif Alquwatly
Project-URL: Homepage, http://github.com/YoosifPlasma/Programs/tags
Requires-Python: >=3.8
License-File: LICENSE
Dynamic: license-file
